aiocmcapi/__init__.py
aiocmcapi/client.py
aiocmcapi/currency.py
aiocmcapi/exceptions.py
aiocmcapi-0.7.3.dist-info/LICENSE
aiocmcapi-0.7.3.dist-info/METADATA
aiocmcapi-0.7.3.dist-info/WHEEL
aiocmcapi-0.7.3.dist-info/top_level.txt
aiocmcapi-0.7.3.dist-info/RECORD
