Metadata-Version: 2.1
Name: aiocmcapi
Version: 0.7.3
Summary: Async wrapper for CoinMarketCap API
Author-email: alobuzy <amozebus@gmail.com>
Requires-Python: >=3.10
License-File: LICENSE
Requires-Dist: aiohttp >=3.9.5
